bluer_sandbox/__init__.py
bluer_sandbox/__main__.py
bluer_sandbox/config.env
bluer_sandbox/env.py
bluer_sandbox/host.py
bluer_sandbox/logger.py
bluer_sandbox/notebooks.py
bluer_sandbox/.abcli/abcli.sh
bluer_sandbox/.abcli/actions.sh
bluer_sandbox/.abcli/alias.sh
bluer_sandbox/.abcli/arvancloud.sh
bluer_sandbox/.abcli/aws.sh
bluer_sandbox/.abcli/bluer_sandbox.sh
bluer_sandbox/.abcli/docker.sh
bluer_sandbox/.abcli/interview.sh
bluer_sandbox/.abcli/jupyter-notebook.sh
bluer_sandbox/.abcli/offline_llm.sh
bluer_sandbox/.abcli/parser.sh
bluer_sandbox/.abcli/speedtest.sh
bluer_sandbox/.abcli/tor.sh
bluer_sandbox/.abcli/v2ray.sh
bluer_sandbox/.abcli/village.sh
bluer_sandbox/.abcli/arvancloud/seed.sh
bluer_sandbox/.abcli/arvancloud/ssh.sh
bluer_sandbox/.abcli/aws/seed.sh
bluer_sandbox/.abcli/docker/browse.sh
bluer_sandbox/.abcli/docker/build.sh
bluer_sandbox/.abcli/docker/clear.sh
bluer_sandbox/.abcli/docker/eval.sh
bluer_sandbox/.abcli/docker/push.sh
bluer_sandbox/.abcli/docker/run.sh
bluer_sandbox/.abcli/docker/seed.sh
bluer_sandbox/.abcli/jupyter-notebook/build.sh
bluer_sandbox/.abcli/jupyter-notebook/code.sh
bluer_sandbox/.abcli/jupyter-notebook/connect.sh
bluer_sandbox/.abcli/jupyter-notebook/create.sh
bluer_sandbox/.abcli/jupyter-notebook/host.sh
bluer_sandbox/.abcli/jupyter-notebook/open.sh
bluer_sandbox/.abcli/offline_llm/build.sh
bluer_sandbox/.abcli/offline_llm/chat.sh
bluer_sandbox/.abcli/offline_llm/create_env.sh
bluer_sandbox/.abcli/offline_llm/model.sh
bluer_sandbox/.abcli/offline_llm/prompt.sh
bluer_sandbox/.abcli/offline_llm/model/download.sh
bluer_sandbox/.abcli/offline_llm/model/get.sh
bluer_sandbox/.abcli/parser/parse.sh
bluer_sandbox/.abcli/tests/README.sh
bluer_sandbox/.abcli/tests/arvancloud_seed.sh
bluer_sandbox/.abcli/tests/aws_seed.sh
bluer_sandbox/.abcli/tests/docker_seed.sh
bluer_sandbox/.abcli/tests/help.sh
bluer_sandbox/.abcli/tests/offline_llm_model_download.sh
bluer_sandbox/.abcli/tests/offline_llm_model_get.sh
bluer_sandbox-5.540.1.dist-info/licenses/LICENSE
bluer_sandbox-5.540.1.dist-info/METADATA
bluer_sandbox-5.540.1.dist-info/WHEEL
bluer_sandbox-5.540.1.dist-info/top_level.txt
bluer_sandbox-5.540.1.dist-info/RECORD
