Metadata-Version: 2.4
Name: bluer_sandbox
Version: 5.540.1
Summary: 🌀 A sandbox for ideas and experiments.
Home-page: https://github.com/kamangir/bluer-sandbox
Author: Arash Abadpour (Kamangir)
Author-email: arash.abadpour@gmail.com
License: CC0-1.0
Classifier: Programming Language :: Python :: 3
Classifier: Programming Language :: Unix Shell
Classifier: Operating System :: OS Independent
License-File: LICENSE
Requires-Dist: bluer_ai
Requires-Dist: beautifulsoup4
Requires-Dist: huggingface-hub[cli]
Requires-Dist: ipdb
Provides-Extra: llama
Requires-Dist: llama-cpp-python; extra == "llama"
Dynamic: author
Dynamic: author-email
Dynamic: classifier
Dynamic: description
Dynamic: description-content-type
Dynamic: home-page
Dynamic: license
Dynamic: license-file
Dynamic: provides-extra
Dynamic: requires-dist
Dynamic: summary
